{
  "summary": {
    "title": "tt11",
    "owner": "asd",
    "description": "asd"
  },
  "detail": {
    "contributors": [],
    "diagrams": [
      {
        "title": "h",
        "thumbnail": "./public/content/images/thumbnail.jpg",
        "id": 0,
        "diagramJson": {
          "cells": [
            {
              "type": "tm.Actor",
              "size": {
                "width": 160,
                "height": 80
              },
              "position": {
                "x": 50,
                "y": 50
              },
              "angle": 0,
              "id": "388309b7-6651-46e7-84a0-3b10f17fb808",
              "z": 1,
              "hasOpenThreats": false,
              "attrs": {
                ".element-shape": {
                  "class": "element-shape hasNoOpenThreats isInScope"
                },
                "text": {
                  "text": "actor 0"
                },
                ".element-text": {
                  "class": "element-text hasNoOpenThreats isInScope"
                }
              }
            }
          ]
        },
        "size": {
          "height": 590,
          "width": 790
        }
      }
    ],
    "reviewer": "asd"
  }
}